hashable_ndframes/__init__.py
hashable_ndframes/hashable_ndframes.py
hashable_ndframes/py.typed
hashable_ndframes-0.1.3.dist-info/LICENSE
hashable_ndframes-0.1.3.dist-info/WHEEL
hashable_ndframes-0.1.3.dist-info/METADATA
hashable_ndframes-0.1.3.dist-info/RECORD
